setup.py
Imagegen.egg-info/PKG-INFO
Imagegen.egg-info/SOURCES.txt
Imagegen.egg-info/dependency_links.txt
Imagegen.egg-info/requires.txt
Imagegen.egg-info/top_level.txt
imagegen/__init__.py
imagegen/graphgen.py