Metadata-Version: 2.1
Name: Imagegen
Version: 0.2
Summary: HomeWork project for graph generation
Home-page: https://pypi.org/pypi
License: UNKNOWN
Platform: UNKNOWN
